cfn_macro_common/__init__.py
cfn_macro_common/bucket.py
cfn_macro_common/cfn_macro_common.py
cfn_macro_common/iam.py
cfn_macro_common/mappings.py
cfn_macro_common/outputs.py
cfn_macro_common/parameters.py
cfn_macro_common/templates.py
cfn_macro_common-0.1.0.dist-info/AUTHORS.rst
cfn_macro_common-0.1.0.dist-info/LICENSE
cfn_macro_common-0.1.0.dist-info/METADATA
cfn_macro_common-0.1.0.dist-info/WHEEL
cfn_macro_common-0.1.0.dist-info/entry_points.txt
cfn_macro_common-0.1.0.dist-info/top_level.txt
cfn_macro_common-0.1.0.dist-info/RECORD
