Metadata-Version: 2.1
Name: cfn-macro-common
Version: 0.1.0
Summary: CFN Macro Common Lib
Home-page: https://github.com/johnpreston/cfn_macro_common
Author: John Mille
Author-email: JohnPreston@users.noreply.github.com
License: Apache Software License 2.0
Keywords: cfn_macro_common
Platform: UNKNOWN
Classifier: Development Status :: 2 - Pre-Alpha
Classifier: Intended Audience :: Developers
Classifier: License :: OSI Approved :: Apache Software License
Classifier: Natural Language :: English
Classifier: Programming Language :: Python :: 3
Classifier: Programming Language :: Python :: 3.6
Classifier: Programming Language :: Python :: 3.7
Requires-Dist: troposphere (>=2.5.0)
